tltsne/__init__.py
tltsne-0.0.2.data/scripts/tltsne
tltsne-0.0.2.dist-info/LICENSE
tltsne-0.0.2.dist-info/METADATA
tltsne-0.0.2.dist-info/WHEEL
tltsne-0.0.2.dist-info/top_level.txt
tltsne-0.0.2.dist-info/RECORD
