Metadata-Version: 2.1
Name: tltsne
Version: 0.0.2
Summary: Time-lagged t-SNE of molecular trajectories
Home-page: https://github.com/spiwokv/tltsne
Author: Vojtech Spiwok
Author-email: spiwokv@vscht.cz
License: UNKNOWN
Platform: UNKNOWN
Classifier: Programming Language :: Python
Classifier: License :: OSI Approved :: MIT License
Classifier: Operating System :: OS Independent
Classifier: Development Status :: 2 - Pre-Alpha
Classifier: Topic :: Scientific/Engineering :: Chemistry
Requires-Dist: scipy
Requires-Dist: sklearn
Requires-Dist: pyemma
Requires-Dist: mdtraj
Requires-Dist: argparse
Requires-Dist: datetime
Requires-Dist: codecov
